{
  "userStatus": "speaking",
  "speakerDetails": "API basics using Postman",
  "isVirtual": true,
  "isInPerson": false,
  "color": "#eb7545",
  "name": "APIs 101 with Postman",
  "description": "The virtual event is designed to provide an introduction to the basics of APIs using Postman. Participants will learn how to use Postman, a popular tool for working with APIs, to send and receive requests and understand the basic concepts of APIs. Participants will also have the opportunity to ask questions and interact with the instructor and other attendees. By the end of the event, participants will have a solid foundation in APIs and be able to apply their new knowledge to their own projects.",
  "date": {
    "start": "2023-03-09T20:00:00.000+03:00",
    "end": "2023-03-09T21:30:00.000+03:00"
  },
  "url": "https://bit.ly/APIs_101_with_Postman"
}
