{
  "name": "Wayne O'Mahony",
  "bio": "Open Source Newbie!",
  "links": [
    {
      "name": "Follow me on GitHub",
      "url": "https://github.com/wayneomahony",
      "icon": "FaGithub"
    },
    {
      "name": "Follow me on Twitter",
      "url": "https://twitter.com/sumosaurus",
      "icon": "FaTwitter"
    }
  ],
  "milestones": [
    {
      "title": "Submitted MSc Thesis",
      "date": "September 2022",
      "icon": "FaDollarSign",
      "color": "grey",
      "description": "Submitted MSc Thesis"
    }
  ]
}
